stremthru/__init__.py
stremthru/client.py
stremthru/error.py
stremthru/version.py
stremthru-0.5.2.dist-info/LICENSE
stremthru-0.5.2.dist-info/METADATA
stremthru-0.5.2.dist-info/WHEEL
stremthru-0.5.2.dist-info/entry_points.txt
stremthru-0.5.2.dist-info/RECORD
