Metadata-Version: 2.3
Name: stremthru
Version: 0.5.2
Summary: SDK for StremThru
License: MIT
Author: Munif Tanjim
Author-email: hello@muniftanjim.dev
Requires-Python: >=3.10,<4.0
Classifier: License :: OSI Approved :: MIT License
Classifier: Programming Language :: Python :: 3
Classifier: Programming Language :: Python :: 3.10
Classifier: Programming Language :: Python :: 3.11
Classifier: Programming Language :: Python :: 3.12
Classifier: Programming Language :: Python :: 3.13
Requires-Dist: aiohttp (>=3.11.9,<4.0.0)
